{
  "bookNumber": 19,
  "book": "Psalms",
  "chapter": 91,
  "verses": {
    "1": "الَّذِي يَسْكُنُ فِي سِتْرِ الْعَلِيِّ، يَرْتَاحُ فِي ظِلِّ الْقَدِيرِ.",
    "2": "أَقُولُ لِرَبِّي: ”أَنْتَ مَلْجَأِي وَحِصْنِي وَإِلَهِيَ الَّذِي أَتَوَكَّلُ عَلَيْهِ.“",
    "3": "رَبُّنَا يُنَجِّيكَ مِنْ فَخِّ الصَّيَّادِ، وَمِنَ الْوَبَأِ الْمُهْلِكِ.",
    "4": "بِرِيشِهِ يُظَلِّلُكَ، وَتَحْتَ أَجْنِحَتِهِ تَحْتَمِي. أَمَانَتُهُ هِيَ تُرْسُكَ وَدِرْعُكَ.",
    "5": "فَلَا تَخَافُ مِنْ هَوْلِ اللَّيْلِ، وَلَا مِنْ سَهْمٍ يَطِيرُ فِي النَّهَارِ،",
    "6": "وَلَا مِنْ وَبَأٍ يَأْتِي فِي الظَّلَامِ، وَلَا مِنْ بَلِيَّةٍ تُهْلِكُ فِي الظَّهِيرَةِ.",
    "7": "يَسْقُطُ عَنْ جَانِبِكَ أَلْفٌ وَعَنْ يَمِينِكَ 10 آلَافٍ، وَأَنْتَ لَا يَمَسُّكَ سُوءٌ.",
    "8": "تَنْظُرُ فَقَطْ بِعَيْنَيْكَ، وَتَرَى عِقَابَ الْأَشْرَارِ.",
    "9": "إِنْ جَعَلْتَ اللهَ مَلْجَأَكَ، إِنْ جَعَلْتَ الْعَلِيَّ حِمَاكَ،",
    "10": "لَا يُصِيبُكَ شَرٌّ، وَلَا تَقْتَرِبُ مُصِيبَةٌ مِنْ مَسْكَنِكَ.",
    "11": "لِأَنَّهُ يُوصِي مَلَائِكَتَهُ بِكَ لِيَحْرُسُوكَ فِي كُلِّ خَطْوَةٍ تَخْطُوهَا.",
    "12": "عَلَى أَيْدِيهِمْ يَحْمِلُونَكَ، فَلَا تَصْدِمُ رِجْلَكَ بِحَجَرٍ.",
    "13": "تَدُوسُ عَلَى الْأَسَدِ وَالثُّعْبَانِ، تَطَأُ عَلَى الشِّبْلِ وَالْحَيَّةِ.",
    "14": "وَيَقُولُ اللهُ: ”أُنَجِّيكَ لِأَنَّكَ تُحِبُّنِي، أَحْمِيكَ لِأَنَّكَ تَعْرِفُنِي.",
    "15": "تَدْعُونِي فَأَسْتَجِيبُ لَكَ. فِي الضِّيقِ أَنَا مَعَكَ. أُنْقِذُكَ وَأُكْرِمُكَ.",
    "16": "أُشْبِعُكَ بِعُمْرٍ طَوِيلٍ، وَأُرِيكَ نَجَاتِي.“"
  }
}