{
  "bookNumber": 19,
  "book": "Psalms",
  "chapter": 112,
  "verses": {
    "1": "Yah’ı övün! Ne mutlu Yahve'den korkan insana, O’nun buyruklarından büyük zevk alana.",
    "2": "Onun soyu ülkede kudretli olacak. Doğruların kuşağı kutsanacak.",
    "3": "Bolluk ve zenginlik onun evindedir. Onun doğruluğu sonsuza dek sürer.",
    "4": "Doğrular için karanlıkta ışık doğar, Lütufkâr, merhametli ve adildir onlar.",
    "5": "Lütfedenin ve ödünç verenin durumu iyidir. Yargıda davasını sürdürür.",
    "6": "Çünkü o asla sarsılmaz. Doğrular sonsuza dek hatırlanır.",
    "7": "Kötü haberden korkmaz. Yüreği kararlıdır, Yahve’ye güvenir.",
    "8": "Yüreği sağlamdır. Sonunda düşmanlarını gördüğünde korkmaz.",
    "9": "O dağıttı, yoksullara verdi. Doğruluğu sonsuza dek durur. Boynuzu saygınlıkla yükselir.",
    "10": "Kötü kişi bunu görüp dertlenir. Dişlerini gıcırdatır, eriyip gider. Kötülerin dileği yok olur."
  }
}