{
  "bookNumber": 19,
  "book": "Psalms",
  "chapter": 133,
  "verses": {
    "1": "Masdan ninyo, na pagkabuti at pagkaligaya sa mga magkakapatid na magsitahang magkakasama sa pagkakaisa!",
    "2": "Parang mahalagang langis sa ulo, na tumutulo sa balbas, sa makatuwid bagay sa balbas ni Aaron. Na tumulo sa laylayan ng kaniyang mga suot;",
    "3": "Gaya ng hamog sa Hermon, na tumutulo sa mga bundok ng Sion: sapagkat doon pinarating ng Panginoon ang pagpapala, sa makatuwid bagay ang buhay na magpakailan pa man."
  }
}