{
  "bookNumber": 23,
  "book": "Isaiah",
  "chapter": 12,
  "verses": {
    "1": "وتقول في ذلك اليوم احمدك يا رب لانه اذ غضبت عليّ ارتد غضبك فتعزيني.",
    "2": "هوذا الله خلاصي فاطمئن ولا ارتعب لان ياه يهوه قوتي وترنيمتي وقد صار لي خلاصا.",
    "3": "فتستقون مياها بفرح من ينابيع الخلاص.",
    "4": "وتقولون في ذلك اليوم احمدوا الرب ادعوا باسمه عرّفوا بين الشعوب بافعاله ذكّروا بان اسمه قد تعالى.",
    "5": "رنموا للرب لانه قد صنع مفتخرا. ليكن هذا معروفا في كل الارض.",
    "6": "صوّتي واهتفي يا ساكنة صهيون لان قدوس اسرائيل عظيم في وسطك"
  }
}