{
  "bookNumber": 60,
  "book": "1 Peter",
  "chapter": 5,
  "verses": {
    "1": "اطلب الى الشيوخ الذين بينكم انا الشيخ رفيقهم والشاهد لآلام المسيح وشريك المجد العتيد ان يعلن",
    "2": "ارعوا رعية الله التي بينكم نظّارا لا عن اضطرار بل بالاختيار ولا لربح قبيح بل بنشاط.",
    "3": "ولا كمن يسود على الانصبة بل صائرين امثلة للرعية",
    "4": "ومتى ظهر رئيس الرعاة تنالون اكليل المجد الذي لا يبلى",
    "5": "كذلك ايها الاحداث اخضعوا للشيوخ وكونوا جميعا خاضعين بعضكم لبعض وتسربلوا بالتواضع لان الله يقاوم المستكبرين واما المتواضعون فيعطيهم نعمة.",
    "6": "فتواضعوا تحت يد الله القوية لكي يرفعكم في حينه",
    "7": "ملقين كل همكم عليه لانه هو يعتني بكم",
    "8": "اصحوا واسهروا لان ابليس خصمكم كأسد زائر يجول ملتمسا من يبتلعه هو.",
    "9": "فقاوموه راسخين في الايمان عالمين ان نفس هذه الآلام تجرى على اخوتكم الذين في العالم",
    "10": "واله كل نعمة الذي دعانا الى مجده الابدي في المسيح يسوع بعدما تألمتم يسيرا هو يكملكم ويثبتكم ويقويكم ويمكنكم",
    "11": "له المجد والسلطان الى ابد الآبدين. آمين",
    "12": "بيد سلوانس الاخ الامين كما اظن كتبت اليكم بكلمات قليلة واعظا وشاهدا ان هذه هي نعمة الله الحقيقية التي فيها تقومون.",
    "13": "تسلم عليكم التي في بابل المختارة معكم ومرقس ابني.",
    "14": "سلموا بعضكم على بعض بقبلة المحبة. سلام لكم جميعكم الذين في المسيح يسوع. آمين"
  }
}